{
	"required": true,
	"package": "gobby.mixin",
	"compatibilityLevel": "JAVA_21",
	"client": [
		"MixinMinecraftClient",
		"MixinMouse",
		"MixinMessageHandler",
      	"MixinKeyboard",
		"MixinScreen",
		"MixinItemStack",
		"render.MixinWorldRenderer",
		"render.MixinLightmapTextureManager",
		"render.MixinSplashTextResourceSupplier",
		"render.MixinInGameOverlayRenderer",
		"render.MixinInGameHud",
		"essentials.MixinSearchbar",
		"accessor.MinecraftClientAccessor",
		"accessor.KeyBindingAccessor",
		"network.MixinClientPlayNetworkHandler",
		"network.MixinClientConnection",
		"MixinFabricLoaderImpl",
		"MixinClientWorld",
		"MixinParticleManager"
	],
	"injectors": {
		"defaultRequire": 1
	},
	"overwrites": {
		"requireAnnotations": true
	}
}